{
  "version": 3,
  "cmakeMinimumRequired": { "major": 3, "minor": 19, "patch": 0 },
  "configurePresets": [
    {
      "name": "windows-default",
      "displayName": "Windows MSVC (shared defaults)",
      "generator": "Ninja",
      "binaryDir": "${sourceDir}/build",
      "cacheVariables": {
        "CMAKE_CXX_STANDARD": "17",
        "CMAKE_PREFIX_PATH": "C:/Qt/6.10.2/msvc2022_64"
      }
    }
  ],
  "buildPresets": [
    {
      "name": "debug",
      "displayName": "Debug Build",
      "configurePreset": "windows-default",
      "configuration": "Debug"
    },
    {
      "name": "release",
      "displayName": "Release Build",
      "configurePreset": "windows-default",
      "configuration": "Release"
    }
  ]
}